latex_components_generator/__init__.py
latex_components_generator/image_latex_generator.py
latex_components_generator/table_latex_generator.py
latex_components_generator-1.0.2.dist-info/METADATA
latex_components_generator-1.0.2.dist-info/WHEEL
latex_components_generator-1.0.2.dist-info/RECORD
